{
  "Requirement": [
    {
      "title": "Java developer",
      "choose_existing_requirement": "Software Developer",
      "job_title": "Java developer",
      "job_location": "Chennai",
      "employment_type": "Full Time",
      "industry": "IT",
      "functional_area": "Human Resources",
      "description": "hii hlo",
      "currency": "INR",
      "minimum_salary": "30000",
      "maximum_salary": "50000",
      "vacancies": "6",
      "brief_candidate_description": "hhiii",
      "educational_qualifications": "BE",
      "minimum": "1",
      "maximum": "1",
      "must_have_keywords": "IT",
      "optional_keywords": "Hadoop",
      "questionnaire": "Are you available immediately ?",
      "contact_person": "John Doe",
      "company_name": "First Meridian",
      "phone_number": "9347128345",
      "about_company": "Good MNC ",
      "company_website": "www.infovision.com",
      "select_recruiters": "Olivia Rhye",
      "positions_closed": 3,
      "status": "InActive",
      "id": 7,
      "Text": "Bold",
      "Role": "Software Developer-I"
    },
    {
      "title": "Python developer",
      "choose_existing_requirement": "Software Developer",
      "job_title": "Python Developer",
      "job_location": "Hyderabad",
      "employment_type": "Part Time",
      "industry": "IT",
      "functional_area": "IT",
      "description": "Job ",
      "currency": "INR",
      "minimum_salary": "45000",
      "maximum_salary": "60000",
      "vacancies": "4",
      "brief_candidate_description": "hiii",
      "educational_qualifications": "BE",
      "minimum": "5",
      "maximum": "5",
      "must_have_keywords": "IT",
      "optional_keywords": "Hadoop",
      "questionnaire": "What is your experience ?",
      "contact_person": "KANAMARLAPUDI PRASANTH",
      "company_name": "Pratian",
      "phone_number": "9347128456",
      "about_company": "fnmktgnjtng",
      "company_website": "www.infovision.com",
      "select_recruiters": "Mark",
      "positions_closed": 4,
      "status": "Active",
      "id": 1
    },
    {
      "title": "Data Analyst",
      "choose_existing_requirement": "Software Developer",
      "job_title": "Data Analyst",
      "job_location": "Hyderabad",
      "employment_type": "Full Time",
      "industry": "Banking",
      "functional_area": "Human Resources",
      "description": "This Requirement for freshers",
      "currency": "USD",
      "minimum_salary": "5000",
      "maximum_salary": "7000",
      "vacancies": "3",
      "brief_candidate_description": "Hiii",
      "educational_qualifications": "B.Tech",
      "minimum": "0",
      "maximum": "2",
      "must_have_keywords": "IT",
      "optional_keywords": "CryptoCurrency",
      "questionnaire": "What is your experience ?",
      "contact_person": "John Doe",
      "company_name": "Network Labs",
      "phone_number": "526864582",
      "about_company": "hiii",
      "company_website": "www.infovision.com",
      "select_recruiters": "Olivia Rhye",
      "positions_closed": 3,
      "status": "Active",
      "": "on",
      "id": 2
    },
    {
      "title": "React JS",
      "choose_existing_requirement": "Software Developer",
      "job_title": "React JS",
      "job_location": "Bengaluru",
      "employment_type": "Full Time",
      "industry": "IT",
      "functional_area": "IT",
      "description": "Hii",
      "currency": "INR",
      "minimum_salary": "30000",
      "maximum_salary": "50000",
      "vacancies": "4",
      "brief_candidate_description": "hlo",
      "educational_qualifications": "B.Tech",
      "minimum": "0",
      "maximum": "4",
      "must_have_keywords": "IT",
      "optional_keywords": "BlockChain",
      "questionnaire": "Are you available immediately ?",
      "contact_person": "KANAMARLAPUDI PRASANTH",
      "company_name": "Pratian",
      "phone_number": "09347128304",
      "about_company": "hii",
      "company_website": "www.infovision.com",
      "select_recruiters": "John",
      "positions_closed": 3,
      "status": "Active",
      "id": 3
    },
    {
      "title": "Angular",
      "choose_existing_requirement": "Software Developer",
      "job_title": "Angular",
      "job_location": "Bengaluru",
      "employment_type": "Full Time",
      "industry": "IT",
      "functional_area": "IT",
      "description": "Angular Developer ",
      "currency": "INR",
      "minimum_salary": "50000",
      "maximum_salary": "70000",
      "vacancies": "10",
      "brief_candidate_description": "xhi",
      "educational_qualifications": "B.Tech",
      "minimum": "0",
      "maximum": "2",
      "must_have_keywords": "IT",
      "optional_keywords": "BlockChain",
      "questionnaire": "Are you available immediately ?",
      "contact_person": "John Doe",
      "company_name": "Pratian",
      "phone_number": "9345712856",
      "about_company": "asfghhjk",
      "company_website": "www.infovision.com",
      "select_recruiters": "Olivia Rhye",
      "positions_closed": 3,
      "status": "Active",
      "id": 4
    }
  ],
  "draft": [
    {
      "Requirement": "[No Title]",
      "No": "#ID-239143",
      "TotalPositions": "10",
      "Positionsclosed": "-",
      "Status": "In-Active",
      "Assignedto": "-",
      "LastModified": "6 March 2022",
      "id": 1
    },
    {
      "Requirement": "[No Title]",
      "No": "#ID-239146",
      "TotalPositions": "-",
      "Positionsclosed": "-",
      "Status": "In-Active",
      "Assignedto": "-",
      "LastModified": "4 Feb 2022",
      "id": 2
    },
    {
      "Requirement": "[No Title]",
      "No": "#ID-239149",
      "TotalPositions": "-",
      "Positionsclosed": "-",
      "Status": "In-Active",
      "Assignedto": "-",
      "LastModified": "2 Feb 2022",
      "id": 3
    }
  ]
}